perfectum/all.py
perfectum/anonymize.py
perfectum/asciify.py
perfectum/chain.py
perfectum/collapse_whitespace.py
perfectum/ftfy.py
perfectum/gpt.py
perfectum/link.py
perfectum/lowercase.py
perfectum/ner.py
perfectum/normalize_unicode.py
perfectum/pattern_replace.py
perfectum/remove_punctuation.py
perfectum/replace.py
perfectum/tab_to_whitespace.py
perfectum/translate.py
perfectum/trim.py
perfectum/uppercase.py
perfectum-0.1.6.dist-info/METADATA
perfectum-0.1.6.dist-info/WHEEL
perfectum-0.1.6.dist-info/top_level.txt
perfectum-0.1.6.dist-info/RECORD
