Metadata-Version: 2.4
Name: perfectum
Version: 0.1.6
Summary: Perfect your text processing pipeline.
Author-email: Georgiy Ozhegov <georgiyozhegov.rs@gmail.com>
Requires-Python: >=3.13
Provides-Extra: ftfy
Requires-Dist: ftfy; extra == "ftfy"
Provides-Extra: translate
Requires-Dist: googletrans; extra == "translate"
Provides-Extra: gpt
Requires-Dist: g4f; extra == "gpt"
Provides-Extra: ner
Requires-Dist: slovnet; extra == "ner"
